MANIFEST.in
README.md
apt_requirements.txt
setup.cfg
setup.py
extractor/__init__.py
extractor/extractor.py
pyextractor.egg-info/PKG-INFO
pyextractor.egg-info/SOURCES.txt
pyextractor.egg-info/dependency_links.txt
pyextractor.egg-info/not-zip-safe
pyextractor.egg-info/requires.txt
pyextractor.egg-info/top_level.txt