Metadata-Version: 1.0
Name: pyextractor
Version: 0.6b0
Summary: Command Line Tool to extract data from files
Home-page: https://github.com/petryx/extractor
Author: Marlon Petry
Author-email: marlonpetry@gmail.com
License: BSD
Platform: UNKNOWN
